clarin_spf/__init__.py
clarin_spf/constants.py
clarin_spf/errors.py
clarin_spf/requester.py
clarin_spf/utils.py
clarin_spf/version.py
clarin_spf-0.2.0.dist-info/LICENSE
clarin_spf-0.2.0.dist-info/METADATA
clarin_spf-0.2.0.dist-info/WHEEL
clarin_spf-0.2.0.dist-info/top_level.txt
clarin_spf-0.2.0.dist-info/RECORD
