Metadata-Version: 2.1
Name: clarin_spf
Version: 0.2.0
Summary: A Python package to interact with the CLARIN SPF API to retrieve the 'logged in' cookies necessary to potentially interact with APIs of services that require the authentication.
Author-email: Bram Vanroy <bramvanroy@hotmail.com>
Maintainer-email: Bram Vanroy <bramvanroy@hotmail.com>
License: Apache License
Project-URL: homepage, https://github.com/BramVanroy/clarin_spf
Project-URL: documentation, https://github.com/BramVanroy/clarin_spf
Project-URL: issues, https://github.com/BramVanroy/clarin_spf/issues
Project-URL: repository, https://github.com/BramVanroy/clarin_spf.git
Keywords: CLARIN,authentication,spf
Classifier: Development Status :: 3 - Alpha
Classifier: Intended Audience :: Developers
Classifier: Intended Audience :: Science/Research
Classifier: Operating System :: OS Independent
Classifier: Programming Language :: Python :: 3.10
Classifier: Programming Language :: Python :: 3.11
Classifier: Programming Language :: Python :: 3.12
Requires-Python: >=3.10
License-File: LICENSE
Requires-Dist: playwright <2.0,>=1.48.0
Provides-Extra: dev
Requires-Dist: build ; extra == 'dev'
Requires-Dist: clarin-spf[examples] ; extra == 'dev'
Requires-Dist: pytest ; extra == 'dev'
Requires-Dist: ruff ; extra == 'dev'
Requires-Dist: twine ; extra == 'dev'
Provides-Extra: examples
Requires-Dist: requests ; extra == 'examples'
